flask_ishuman/__init__.py
flask_ishuman/py.typed
flask_ishuman-2.1.2.dist-info/licenses/LICENSE
flask_ishuman-2.1.2.dist-info/METADATA
flask_ishuman-2.1.2.dist-info/WHEEL
flask_ishuman-2.1.2.dist-info/top_level.txt
flask_ishuman-2.1.2.dist-info/zip-safe
flask_ishuman-2.1.2.dist-info/RECORD
