Metadata-Version: 2.4
Name: flask_ishuman
Version: 2.1.2
Summary: simple flask captcha validation
Home-page: https://ari.lt/gh/flask-ishuman
Author: Arija A.
Author-email: ari@ari.lt
License: GPLv3+
Keywords: flask,captcha,recaptcha,audio captcha,image captcha,human validation
Classifier: Development Status :: 5 - Production/Stable
Classifier: Environment :: Web Environment
Classifier: Intended Audience :: Developers
Classifier: License :: OSI Approved :: GNU General Public License v3 or later (GPLv3+)
Classifier: Operating System :: OS Independent
Classifier: Programming Language :: Python :: 3
Classifier: Programming Language :: Python :: 3.9
Classifier: Programming Language :: Python :: 3.10
Classifier: Programming Language :: Python :: 3.11
Classifier: Programming Language :: Python :: 3.12
Classifier: Programming Language :: Python :: 3.13
Classifier: Topic :: Internet :: WWW/HTTP
Classifier: Topic :: Software Development :: Libraries :: Python Modules
Classifier: Topic :: Security
Classifier: Typing :: Typed
License-File: LICENSE
Requires-Dist: more-captcha
Requires-Dist: flask
Requires-Dist: types-Flask
Dynamic: license-file
